pybsts.cpython-36m-darwin.so
causal_impact/__init__.py
causal_impact/causal_impact.py
causal_impact/setup.py
pybsts-1.0.4.dist-info/LICENSE
pybsts-1.0.4.dist-info/METADATA
pybsts-1.0.4.dist-info/WHEEL
pybsts-1.0.4.dist-info/top_level.txt
pybsts-1.0.4.dist-info/RECORD
